metabase_tools/__init__.py
metabase_tools/endpoints/__init__.py
metabase_tools/endpoints/activity_endpoint.py
metabase_tools/endpoints/alerts_endpoint.py
metabase_tools/endpoints/cards_endpoint.py
metabase_tools/endpoints/collections_endpoint.py
metabase_tools/endpoints/dashboard_endpoint.py
metabase_tools/endpoints/databases_endpoint.py
metabase_tools/endpoints/generic_endpoint.py
metabase_tools/endpoints/users_endpoint.py
metabase_tools/exceptions.py
metabase_tools/metabase.py
metabase_tools/models/__init__.py
metabase_tools/models/activity_model.py
metabase_tools/models/alert_model.py
metabase_tools/models/card_model.py
metabase_tools/models/collection_model.py
metabase_tools/models/dashboard_model.py
metabase_tools/models/database_model.py
metabase_tools/models/generic_model.py
metabase_tools/models/server_settings.py
metabase_tools/models/user_model.py
metabase_tools/tools/__init__.py
metabase_tools/tools/tools.py
metabase_tools/utils/__init__.py
metabase_tools/utils/logging_utils.py
metabase_tools-0.16.0.dist-info/LICENSE.md
metabase_tools-0.16.0.dist-info/METADATA
metabase_tools-0.16.0.dist-info/WHEEL
metabase_tools-0.16.0.dist-info/RECORD
