Metadata-Version: 2.1
Name: metabase-tools
Version: 0.16.0
Summary: Unofficial API wrapper for Metabase plus additional helper tools
Home-page: https://j01101111sh.github.io/metabase-tools/
License: MIT
Author: Josh Odell
Author-email: j01101111sh@gmail.com
Maintainer: Josh Odell
Maintainer-email: j01101111sh@gmail.com
Requires-Python: >=3.10,<3.13
Classifier: Development Status :: 3 - Alpha
Classifier: Intended Audience :: System Administrators
Classifier: License :: OSI Approved :: MIT License
Classifier: Operating System :: OS Independent
Classifier: Programming Language :: Cython
Classifier: Programming Language :: Python
Classifier: Programming Language :: Python :: 3
Classifier: Programming Language :: Python :: 3.10
Classifier: Programming Language :: Python :: 3.11
Classifier: Programming Language :: Python :: 3.12
Classifier: Programming Language :: Python :: 3 :: Only
Classifier: Typing :: Typed
Requires-Dist: packaging (>=21.3,<24.0)
Requires-Dist: pydantic (>=1.9.1,<2.0.0)
Requires-Dist: requests (>=2.28.1,<3.0.0)
Requires-Dist: types-requests (>=2.28.9,<3.0.0)
Project-URL: Documentation, https://j01101111sh.github.io/metabase-tools/
Project-URL: Repository, https://github.com/j01101111sh/metabase-tools
